bioino/__init__.py
bioino/cli.py
bioino/fasta.py
bioino/gff.py
bioino/tables.py
bioino-0.0.2.post1.dist-info/LICENSE
bioino-0.0.2.post1.dist-info/METADATA
bioino-0.0.2.post1.dist-info/WHEEL
bioino-0.0.2.post1.dist-info/entry_points.txt
bioino-0.0.2.post1.dist-info/top_level.txt
bioino-0.0.2.post1.dist-info/RECORD
