Metadata-Version: 2.1
Name: bioino
Version: 0.0.2.post1
Summary: Lightweight IO and conversion for bioinformatics file formats.
Author-email: Eachan Johnson <eachan.johnson@crick.ac.uk>
Project-URL: Homepage, https://github.com/scbirlab/bioino
Project-URL: Bug Tracker, https://github.com/scbirlab/bioino/issues
Keywords: biology,bioinformatics,science,io
Classifier: Development Status :: 3 - Alpha
Classifier: Intended Audience :: Science/Research
Classifier: Topic :: Scientific/Engineering :: Bio-Informatics
Classifier: License :: OSI Approved :: MIT License
Classifier: Programming Language :: Python :: 3.8
Classifier: Programming Language :: Python :: 3.9
Classifier: Programming Language :: Python :: 3.10
Classifier: Programming Language :: Python :: 3.11
Classifier: Programming Language :: Python :: 3 :: Only
Requires-Python: >=3.8
License-File: LICENSE
Requires-Dist: carabiner-tools[pd] >=0.0.1.post2
Requires-Dist: pandas
